karabo_gui-3.0.8.dist-info/licenses/LICENSE.md
karabogui/__init__.py
karabogui/_version.py
karabogui/access.py
karabogui/actions.py
karabogui/api.py
karabogui/background.py
karabogui/conftest.py
karabogui/const.py
karabogui/debug.py
karabogui/events.py
karabogui/generic_scenes.py
karabogui/indicators.py
karabogui/itemtypes.py
karabogui/logger.py
karabogui/mainwindow.py
karabogui/messagebox.py
karabogui/pathparser.py
karabogui/request.py
karabogui/util.py
karabogui/validators.py
karabogui/binding/__init__.py
karabogui/binding/api.py
karabogui/binding/binding_types.py
karabogui/binding/builder.py
karabogui/binding/config.py
karabogui/binding/enums.py
karabogui/binding/proxy.py
karabogui/binding/trait_types.py
karabogui/binding/util.py
karabogui/binding/validate.py
karabogui/binding/tests/__init__.py
karabogui/binding/tests/benchmark.py
karabogui/binding/tests/test_config.py
karabogui/binding/tests/test_proxy.py
karabogui/binding/tests/test_trait_types.py
karabogui/binding/tests/test_types.py
karabogui/binding/tests/test_util.py
karabogui/binding/tests/test_validate.py
karabogui/binding/tests/data/BeckhoffAgilentIonPump.config
karabogui/binding/tests/data/BeckhoffAgilentIonPump.schema
karabogui/binding/tests/data/BeckhoffAnalogInput.config
karabogui/binding/tests/data/BeckhoffAnalogInput.schema
karabogui/binding/tests/data/BeckhoffCom.config
karabogui/binding/tests/data/BeckhoffCom.schema
karabogui/binding/tests/data/BeckhoffMC2.config
karabogui/binding/tests/data/BeckhoffMC2.schema
karabogui/binding/tests/data/LimaBaslerCamera.config
karabogui/binding/tests/data/LimaBaslerCamera.schema
karabogui/configurator/__init__.py
karabogui/configurator/api.py
karabogui/configurator/edit_delegate.py
karabogui/configurator/filter_model.py
karabogui/configurator/qt_item_model.py
karabogui/configurator/slot_delegate.py
karabogui/configurator/utils.py
karabogui/configurator/value_delegate.py
karabogui/configurator/view.py
karabogui/configurator/dialog/__init__.py
karabogui/configurator/dialog/table_view.py
karabo_gui-3.0.8.dist-info/METADATA
karabo_gui-3.0.8.dist-info/WHEEL
karabo_gui-3.0.8.dist-info/entry_points.txt
karabo_gui-3.0.8.dist-info/top_level.txt
karabo_gui-3.0.8.dist-info/RECORD
