Metadata-Version: 2.4
Name: karabo.gui
Version: 3.0.8
Summary: Karabo's Graphical User Interface
Author-email: European XFEL GmbH <opensource@xfel.eu>
Maintainer-email: "S. Hauf" <steffen.hauf@xfel.eu>, "D. Goeries" <dennis.goeries@xfel.eu>
License-Expression: GPL-3.0-or-later
Project-URL: Homepage, https://github.com/European-XFEL/Karabo
Project-URL: Bug Reports, https://github.com/European-XFEL/Karabo/issues
Project-URL: Source, https://github.com/European-XFEL/Karabo
Keywords: Karabo,SCADA,PyQt,control system
Classifier: Development Status :: 5 - Production/Stable
Classifier: Intended Audience :: Developers
Classifier: Intended Audience :: Science/Research
Requires-Python: >=3.12
License-File: LICENSE.md
Requires-Dist: cycler==0.10.0
Requires-Dist: flake8==6.1.0
Requires-Dist: isort==5.8.0
Requires-Dist: karabo-native==3.0.8
Requires-Dist: lttbc==0.3.0
Requires-Dist: lxml>=5.3.2
Requires-Dist: natsort==6.2.0
Requires-Dist: numpy==2.1.3
Requires-Dist: pint>=0.24.4
Requires-Dist: pyqt5>=5.15
Requires-Dist: pyqtgraph==0.13.3
Requires-Dist: pytest-cov==2.12.1
Requires-Dist: pytest-mock==3.6.1
Requires-Dist: pytest-qt==4.3.1
Requires-Dist: pytest-subtests==0.11.0
Requires-Dist: pytest-xdist>=3.5
Requires-Dist: pytest>=8.2
Requires-Dist: pyyaml==6.0.1
Requires-Dist: qscintilla>=2.14.1
Requires-Dist: qtpy==2.4.1
Requires-Dist: requests==2.28.1
Requires-Dist: scipy==1.14.0
Requires-Dist: tabulate>=0.8.9
Requires-Dist: traits==6.4.3
Requires-Dist: typing-extensions==4.12.2
Requires-Dist: setuptools
Dynamic: license-file
